package_name/__init__.py
package_name/file1_name.py
Primeiro_Pacote-0.0.1.dist-info/METADATA
Primeiro_Pacote-0.0.1.dist-info/WHEEL
Primeiro_Pacote-0.0.1.dist-info/top_level.txt
Primeiro_Pacote-0.0.1.dist-info/RECORD
