Metadata-Version: 2.1
Name: Primeiro-Pacote
Version: 0.0.1
Summary: Pacote diz olá
Home-page: https://github.com/Rayron2012/Dio_1_Repositorio_Bootcamp.git
Author: Rayron Soares
Author-email: rayron2013@gmail.com
License: UNKNOWN
Platform: UNKNOWN
Requires-Python: >=3.8
